LICENSE
MANIFEST.in
README.md
pyproject.toml
configs/default.yaml
src/concierge/__init__.py
src/concierge/config.py
src/concierge/communications/__init__.py
src/concierge/communications/base.py
src/concierge/communications/error.py
src/concierge/communications/handshake.py
src/concierge/communications/messages.py
src/concierge/communications/stage.py
src/concierge/communications/state_input_required.py
src/concierge/communications/state_update.py
src/concierge/communications/task_result.py
src/concierge/communications/transition_result.py
src/concierge/core/__init__.py
src/concierge/core/actions.py
src/concierge/core/builtins.py
src/concierge/core/construct.py
src/concierge/core/postgres_state_manager.py
src/concierge/core/registry.py
src/concierge/core/results.py
src/concierge/core/stage.py
src/concierge/core/state.py
src/concierge/core/state_manager.py
src/concierge/core/task.py
src/concierge/core/types.py
src/concierge/core/workflow.py
src/concierge/engine/__init__.py
src/concierge/engine/language_engine.py
src/concierge/engine/orchestrator.py
src/concierge/external/__init__.py
src/concierge/external/contracts.py
src/concierge/presentations/__init__.py
src/concierge/presentations/base.py
src/concierge/presentations/brief.py
src/concierge/presentations/comprehensive.py
src/concierge/presentations/state_input.py
src/concierge/serving/__init__.py
src/concierge/serving/api.py
src/concierge/serving/http.py
src/concierge/serving/manager.py
src/concierge_awi.egg-info/PKG-INFO
src/concierge_awi.egg-info/SOURCES.txt
src/concierge_awi.egg-info/dependency_links.txt
src/concierge_awi.egg-info/requires.txt
src/concierge_awi.egg-info/top_level.txt