Metadata-Version: 2.1
Name: concierge-awi
Version: 0.1.1
Summary: Declarative framework for building Agentic AI Services
License: # License
Project-URL: Homepage, https://github.com/Agentic-Web-Interfaces/concierge
Project-URL: Repository, https://github.com/Agentic-Web-Interfaces/concierge
Requires-Python: >=3.9
License-File: LICENSE
